ebDiscord/__init__.py
ebDiscord-0.0.1.4.dist-info/LICENSE
ebDiscord-0.0.1.4.dist-info/METADATA
ebDiscord-0.0.1.4.dist-info/WHEEL
ebDiscord-0.0.1.4.dist-info/top_level.txt
ebDiscord-0.0.1.4.dist-info/RECORD
