Metadata-Version: 2.1
Name: ebDiscord
Version: 0.0.1.4
Summary: A way make discord bots with python super easy
Home-page: https://github.com/lol123123f/ebDsicord
Author: SpaceX#1919
Author-email: edgardbu@gmail.com
Classifier: Programming Language :: Python :: 3
Classifier: License :: OSI Approved :: MIT License
Classifier: Operating System :: OS Independent
Requires-Python: >=3.6
License-File: LICENSE
